integration_tests/__init__.py
integration_tests/test_minimal_project.py
integration_tests/test_with_python_package.py
readthedocs_build/__init__.py
readthedocs_build/build.py
readthedocs_build/cli.py
readthedocs_build/test_build.py
readthedocs_build/test_cli.py
readthedocs_build/utils.py
readthedocs_build/builder/__init__.py
readthedocs_build/builder/base.py
readthedocs_build/builder/sphinx.py
readthedocs_build/builder/test_base.py
readthedocs_build/builder/test_sphinx.py
readthedocs_build/builder/test_virtualenv.py
readthedocs_build/builder/utils.py
readthedocs_build/builder/virtualenv.py
readthedocs_build/config/__init__.py
readthedocs_build/config/config.py
readthedocs_build/config/find.py
readthedocs_build/config/parser.py
readthedocs_build/config/test_config.py
readthedocs_build/config/test_find.py
readthedocs_build/config/test_parser.py
readthedocs_build/config/test_validation.py
readthedocs_build/config/validation.py
readthedocs_build/testing/__init__.py
readthedocs_build/testing/test_utils.py
readthedocs_build/testing/utils.py
readthedocs_build-2.0.9.dist-info/DESCRIPTION.rst
readthedocs_build-2.0.9.dist-info/METADATA
readthedocs_build-2.0.9.dist-info/RECORD
readthedocs_build-2.0.9.dist-info/WHEEL
readthedocs_build-2.0.9.dist-info/entry_points.txt
readthedocs_build-2.0.9.dist-info/metadata.json
readthedocs_build-2.0.9.dist-info/top_level.txt
readthedocs_build-2.0.9.dist-info/zip-safe
