Metadata-Version: 2.0
Name: readthedocs-build
Version: 2.0.9
Summary: Build infrastructure for Read the Docs
Home-page: https://readthedocs.org
Author: Eric Holscher
Author-email: eric@ericholscher.com
License: MIT
Platform: UNKNOWN
Requires-Dist: PyYAML (>=3.0)
Requires-Dist: Sphinx (>=1.5.2)
Requires-Dist: Docutils
Requires-Dist: readthedocs-sphinx-ext
Requires-Dist: recommonmark
Requires-Dist: click (>=4.0)
Requires-Dist: virtualenv
Requires-Dist: six
Requires-Dist: mock
